pyrasgo/__init__.py
pyrasgo/config.py
pyrasgo/constants.py
pyrasgo/errors.py
pyrasgo/imports.py
pyrasgo/rasgo.py
pyrasgo/version.py
pyrasgo/api/__init__.py
pyrasgo/api/connection.py
pyrasgo/api/create.py
pyrasgo/api/delete.py
pyrasgo/api/get.py
pyrasgo/api/login.py
pyrasgo/api/publish.py
pyrasgo/api/read.py
pyrasgo/api/session.py
pyrasgo/api/update.py
pyrasgo/primitives/__init__.py
pyrasgo/primitives/dataset.py
pyrasgo/primitives/dbt.py
pyrasgo/schemas/__init__.py
pyrasgo/schemas/attributes.py
pyrasgo/schemas/dataset.py
pyrasgo/schemas/dataset_column.py
pyrasgo/schemas/dw.py
pyrasgo/schemas/dw_operation.py
pyrasgo/schemas/dw_operation_set.py
pyrasgo/schemas/dw_table.py
pyrasgo/schemas/enums.py
pyrasgo/schemas/metric.py
pyrasgo/schemas/offline.py
pyrasgo/schemas/organization.py
pyrasgo/schemas/status_tracking.py
pyrasgo/schemas/transform.py
pyrasgo/schemas/user.py
pyrasgo/storage/__init__.py
pyrasgo/storage/dataframe/__init__.py
pyrasgo/storage/dataframe/utils.py
pyrasgo/storage/datawarehouse/__init__.py
pyrasgo/storage/datawarehouse/bigquery.py
pyrasgo/storage/datawarehouse/connect.py
pyrasgo/storage/datawarehouse/snowflake.py
pyrasgo/storage/datawarehouse/utils.py
pyrasgo/utils/__init__.py
pyrasgo/utils/dbt.py
pyrasgo/utils/naming.py
pyrasgo/utils/polling.py
pyrasgo/utils/rendering.py
pyrasgo/utils/versioning.py
pyrasgo-2023.5.1.dist-info/LICENSE.md
pyrasgo-2023.5.1.dist-info/METADATA
pyrasgo-2023.5.1.dist-info/WHEEL
pyrasgo-2023.5.1.dist-info/top_level.txt
pyrasgo-2023.5.1.dist-info/RECORD
