Metadata-Version: 2.1
Name: pyrasgo
Version: 2023.5.1
Summary: Python interface to the Rasgo API.
Home-page: https://www.rasgoml.com/
Author: Patrick Dougherty
Author-email: patrick@rasgoml.com
License: GNU Affero General Public License v3 or later (AGPLv3+)
Project-URL: Documentation, https://docs.rasgoml.com
Project-URL: Source, https://github.com/rasgointelligence/RasgoSDKPython
Project-URL: Rasgo, https://www.rasgoml.com/
Project-URL: Changelog, https://github.com/rasgointelligence/RasgoSDKPython/blob/master/pyrasgo/CHANGELOG.md
Classifier: Development Status :: 4 - Beta
Classifier: License :: OSI Approved :: GNU Affero General Public License v3 or later (AGPLv3+)
Classifier: Intended Audience :: Science/Research
Classifier: Intended Audience :: Developers
Classifier: Programming Language :: Python :: 3.7
Classifier: Programming Language :: Python :: 3.8
Classifier: Programming Language :: Python :: 3.9
Classifier: Programming Language :: Python :: 3.10
Classifier: Topic :: Scientific/Engineering :: Information Analysis
Requires-Python: >=3.7
License-File: LICENSE.md
Requires-Dist: more-itertools
Requires-Dist: pandas
Requires-Dist: pydantic
Requires-Dist: pydantic-yaml
Requires-Dist: pyyaml
Requires-Dist: rasgotransforms (>=2.2.7)
Requires-Dist: requests
Requires-Dist: snowflake-connector-python
Requires-Dist: snowflake-connector-python[pandas]
Requires-Dist: typing-extensions
Provides-Extra: bigquery
Requires-Dist: db-dtypes ; extra == 'bigquery'
Requires-Dist: google-auth-oauthlib ; extra == 'bigquery'
Requires-Dist: google-cloud-bigquery ; extra == 'bigquery'
Provides-Extra: snowflake
Requires-Dist: snowflake-connector-python ; extra == 'snowflake'
Requires-Dist: snowflake-connector-python[pandas] ; extra == 'snowflake'
